gitlab_webhook_telegram-1.0.1.data/scripts/gwt
gwt/__init__.py
gwt/chats_projects.json
gwt/config.json
gwt/daemon.py
gwt/handlers.py
gwt/main.py
gwt/verified_chats.json
gitlab_webhook_telegram-1.0.1.dist-info/LICENSE
gitlab_webhook_telegram-1.0.1.dist-info/METADATA
gitlab_webhook_telegram-1.0.1.dist-info/WHEEL
gitlab_webhook_telegram-1.0.1.dist-info/top_level.txt
gitlab_webhook_telegram-1.0.1.dist-info/RECORD
