Metadata-Version: 2.1
Name: gitlab-webhook-telegram
Version: 1.0.1
Summary: A simple bot reacting to gitlab webhook
Home-page: http://github.com/nanoy42/gitlab-webhook-telegram
Author: Yoann `Nanoy` Pietri
Author-email: me@nanoy.fr
License: GNU General Public License v3.0
Platform: UNKNOWN
Requires-Dist: docopt
Requires-Dist: python-telegram-bot
